LICENSE
MANIFEST.in
README.md
setup.py
abo/__init__.py
abo/admin.py
abo/choices.py
abo/factories.py
abo/fields.py
abo/models.py
abo/settings.py
abo/signals.py
abo/urls.py
abo/utils.py
abo/views.py
abo/backends/__init__.py
abo/backends/paymill/__init__.py
abo/backends/paymill/apps.py
abo/backends/paymill/events.py
abo/backends/paymill/forms.py
abo/backends/paymill/models.py
abo/backends/paymill/urls.py
abo/backends/paymill/views.py
abo/backends/paymill/webhooks.py
abo/backends/paymill/templates/paymill.html
abo/backends/paymill/templates/paymill_form.html
abo/backends/paymill/tests/__init__.py
abo/backends/paymill/tests/mockups.py
abo/backends/paymill/tests/test_events.py
abo/backends/paymill/tests/test_form.py
abo/backends/paymill/tests/test_views.py
abo/management/__init__.py
abo/management/commands/__init__.py
abo/management/commands/register_webhooks.py
abo/templates/change_card.html
abo/templates/subscription_success.html
abo/tests/__init__.py
abo/tests/mocked_backend_for_events.py
abo/tests/test_events.py
django_abo.egg-info/PKG-INFO
django_abo.egg-info/SOURCES.txt
django_abo.egg-info/dependency_links.txt
django_abo.egg-info/not-zip-safe
django_abo.egg-info/requires.txt
django_abo.egg-info/top_level.txt