Metadata-Version: 1.1
Name: django-abo
Version: 0.1.4
Summary: Recurring payment / subscription handling for Django, supporting different payment gateways
Home-page: https://github.com/ubergrape/django-abo
Author: Stefan Kröner
Author-email: sk@ubergrape.com
License: BSD
Platform: any
Classifier: Development Status :: 4 - Beta
Classifier: Environment :: Web Environment
Classifier: Framework :: Django
Classifier: Intended Audience :: Developers
Classifier: License :: OSI Approved :: BSD License
Classifier: Operating System :: OS Independent
Classifier: Programming Language :: Python
Classifier: Topic :: Software Development :: Libraries :: Python Modules
